notifier/__init__.py
notifier/discord_class.py
notifier/telegram_class.py
notify_function-1.5.2.dist-info/LICENSE
notify_function-1.5.2.dist-info/METADATA
notify_function-1.5.2.dist-info/WHEEL
notify_function-1.5.2.dist-info/top_level.txt
notify_function-1.5.2.dist-info/RECORD
