Metadata-Version: 2.1
Name: notify-function
Version: 1.5.2
Summary: Notify you when a function finished with option to send a email, telegram message or message to discord channel
Home-page: https://github.com/enmanuel-mag/notify_function
Author: Enmanuel Magallanes Pinargote
Author-email: enmanuelmag@cardor.dev
License: UNKNOWN
Platform: UNKNOWN
Classifier: Programming Language :: Python :: 3
Classifier: License :: OSI Approved :: MIT License
Classifier: Operating System :: OS Independent
Requires-Python: >=3.6
License-File: LICENSE
Requires-Dist: requests
Requires-Dist: py-notifier
Requires-Dist: discord-webhook
